bmc/__init__.py
bmc/_bucket.py
bmc/_config.py
bmc/_cp.py
bmc/_group.py
bmc/_ls.py
bmc/_mb.py
bmc/_policy.py
bmc/_rb.py
bmc/_server.py
bmc/_user.py
bmc/_utils.py
bmc/console.py
bmc/heal.py
bmc/info.py
bmc/profile.py
bmc/prometheus.py
bmc/service.py
bmc/top.py
bmc/trace.py
bmc/update.py
tests/__init__.py
tests/test_bmc.py
bmc-0.0.4.dist-info/LICENSE.txt
bmc-0.0.4.dist-info/METADATA
bmc-0.0.4.dist-info/WHEEL
bmc-0.0.4.dist-info/top_level.txt
bmc-0.0.4.dist-info/RECORD
