Metadata-Version: 2.1
Name: bmc
Version: 0.0.4
Summary: Python wrapper for Minio Admin
Home-page: https://big-mama-tech.gitlab.io/bmc/
Author: BIGmama Technology
Author-email: contact@big-mama.io
License: Proprietary
Platform: UNKNOWN
Classifier: Programming Language :: Python
Classifier: Development Status :: 3 - Alpha
Classifier: License :: Other/Proprietary License
Classifier: Natural Language :: English
Classifier: Operating System :: OS Independent
Classifier: Programming Language :: Python :: 3.7
Classifier: Topic :: Scientific/Engineering
